streamdal
