Metadata-Version: 2.1
Name: streamdal
Version: 0.1.5
Summary: Python client SDK for Streamdal's open source observability server
Home-page: https://github.com/streamdal/python-sdk
Author: Streamdal.com
Author-email: engineering@streamdal.com
License: MIT
Platform: UNKNOWN
Classifier: License :: OSI Approved :: MIT License
Classifier: Programming Language :: Python :: 3.8
Classifier: Programming Language :: Python :: 3.9
Classifier: Programming Language :: Python :: 3.10
Classifier: Programming Language :: Python :: 3.11
Requires-Python: >=3.8
License-File: LICENSE
